{
    "Giornata18": {
        "Milo": {
            "link": "https://www.fanta.soccer/it/lega/privata/122355/dettaglipartita/18/10535616/",
            "titolari": {
                "1": "Handanovic S.",
                "2": "Di Lorenzo G.",
                "3": "Tomiyasu T.",
                "4": "Mario Rui",
                "5": "Politano M.",
                "6": "Mckennie W.",
                "7": "Candreva A.",
                "8": "Soriano R.",
                "9": "Farias D.",
                "10": "Ibrahimovic Z.",
                "11": "Ronaldo C."
            },
            "riserve": {
                "1": "Radu I.",
                "2": "Lopez P.",
                "3": "Ghoulam F.",
                "4": "Hysaj E.",
                "5": "Letizia G.",
                "6": "Maggio C.",
                "7": "Malcuit K.",
                "8": "Bennacer I.",
                "9": "Elmas E.",
                "10": "Gagliardini R.",
                "11": "Rog M.",
                "12": null,
                "13": "",
                "14": ""
            },
            "formazione schierata": "√"
        },
        "Zino": {
            "link": "https://www.fanta.soccer/it/lega/privata/122355/dettaglipartita/18/10535616/",
            "titolari": {
                "1": "Silvestri M.",
                "2": "Toloi R.",
                "3": "Mancini G.",
                "4": "Djimsiti B.",
                "5": "Pereyra R.",
                "6": "Brozovic M.",
                "7": "Dominguez N.",
                "8": "Malinovskyi R.",
                "9": "Boga J.",
                "10": "Vlahovic D.",
                "11": "Rebic A."
            },
            "riserve": {
                "1": "Pandur I.",
                "2": "Skorupski L.",
                "3": "De Ligt M.",
                "4": "Caceres M.",
                "5": "Walukiewicz S.",
                "6": "Erlic M.",
                "7": "Sutalo B.",
                "8": "Melegoni F.",
                "9": "Amrabat S.",
                "10": "Kulusevski D.",
                "11": "Cigarini L.",
                "12": "Dzeko E.",
                "13": "Pjaca M.",
                "14": "Ribery F."
            },
            "formazione schierata": "√"
        },
        "Carlo": {
            "link": "https://www.fanta.soccer/it/lega/privata/122355/dettaglipartita/18/10535617/",
            "titolari": {
                "1": "Ospina D.",
                "2": "Augello T.",
                "3": "De Silvestri L.",
                "4": "Acerbi F.",
                "5": "Bonucci L.",
                "6": "Freuler R.",
                "7": "Kucka J.",
                "8": "Rincon T.",
                "9": "Caputo F.",
                "10": "Zapata D.",
                "11": "Galabinov A."
            },
            "riserve": {
                "1": "Meret A.",
                "2": "Contini N.",
                "3": "Alex Sandro",
                "4": "Gagliolo R.",
                "5": "Frabotta G.",
                "6": "Nkoulou N.",
                "7": "Ekdal A.",
                "8": "Schiattarella P.",
                "9": "Maggiore G.",
                "10": "Gomez A.",
                "11": "Tonali S.",
                "12": "Keita B.",
                "13": "Caso G.",
                "14": ""
            },
            "formazione schierata": "√"
        },
        "Sangio": {
            "link": "https://www.fanta.soccer/it/lega/privata/122355/dettaglipartita/18/10535617/",
            "titolari": {
                "1": "Donnarumma G.",
                "2": "Hakimi A.",
                "3": "Biraghi C.",
                "4": "Young A.",
                "5": "Bereszynski B.",
                "6": "Barella N.",
                "7": "Locatelli M.",
                "8": "Zielinski P.",
                "9": "Castillejo S.",
                "10": "Nainggolan R.",
                "11": "Belotti A."
            },
            "riserve": {
                "1": "Tatarusanu C.",
                "2": "Sepe L.",
                "3": "Kumbulla M.",
                "4": "Lovato M.",
                "5": "Fares M.",
                "6": "Cetin M.",
                "7": "Damsgaard M.",
                "8": "Rabiot A.",
                "9": "Verre V.",
                "10": "Sanchez A.",
                "11": "Dybala P.",
                "12": "Di Serio G.",
                "13": "Vergani E.",
                "14": null
            },
            "formazione schierata": "√"
        },
        "Melis": {
            "link": "https://www.fanta.soccer/it/lega/privata/122355/dettaglipartita/18/10535618/",
            "titolari": {
                "1": "Szczesny W.",
                "2": "Criscito D.",
                "3": "Chabot J.",
                "4": "Lykogiannis C.",
                "5": "Faraoni D.",
                "6": "De Roon M.",
                "7": "Arslan T.",
                "8": "Bonaventura G.",
                "9": "Djuricic F.",
                "10": "Calhanoglu H.",
                "11": "Immobile C."
            },
            "riserve": {
                "1": "Piccoli R.",
                "2": "Pedro",
                "3": "Favilli A.",
                "4": "Caicedo F.",
                "5": "Marin R.",
                "6": "Hernani A.",
                "7": "Dabo B.",
                "8": "Pellegrini Lu.",
                "9": "Gosens R.",
                "10": "Caldirola L.",
                "11": "Pinsoglio C.",
                "12": "Buffon G.",
                "13": "",
                "14": ""
            },
            "formazione schierata": "√"
        },
        "Michelone": {
            "link": "https://www.fanta.soccer/it/lega/privata/122355/dettaglipartita/18/10535618/",
            "titolari": {
                "1": "Musso J.",
                "2": "Skriniar M.",
                "3": "Zappa G.",
                "4": "Romero C.",
                "5": "Koulibaly K.",
                "6": "Mkhitaryan H.",
                "7": "Vidal A.",
                "8": "Tameze A.",
                "9": "Bentancur R.",
                "10": "Ilic I.",
                "11": "Osimhen V."
            },
            "riserve": {
                "1": "Kouame' C.",
                "2": "Salcedo E.",
                "3": "Bonazzoli F.",
                "4": "Males D.",
                "5": "Berardi D.",
                "6": "Arthur",
                "7": "Zanellato N.",
                "8": "Molina S.",
                "9": "Rogerio O.",
                "10": "Kyriakopoulos G.",
                "11": "Caldara M.",
                "12": "D'Ambrosio D.",
                "13": "Consigli A.",
                "14": "Scuffet S."
            },
            "formazione schierata": "√"
        },
        "Bisca": {
            "link": "https://www.fanta.soccer/it/lega/privata/122355/dettaglipartita/18/10535619/",
            "titolari": {
                "1": "Dragowski B.",
                "2": "Muldur M.",
                "3": "Chiellini G.",
                "4": "Hernandez T.",
                "5": "De Paul R.",
                "6": "Luis Alberto",
                "7": "Agoume L.",
                "8": "Pellegrini Lo.",
                "9": "Martinez L.",
                "10": "Barrow M.",
                "11": "Simeone G."
            },
            "riserve": {
                "1": "Sirigu S.",
                "2": "Terracciano P.",
                "3": "Yoshida M.",
                "4": "Toljan J.",
                "5": "Hickey A.",
                "6": "Ayhan K.",
                "7": "Vojvoda M.",
                "8": "Pereira A.",
                "9": "Verdi S.",
                "10": "Ricci M.",
                "11": "Ramirez G.",
                "12": "Quagliarella F.",
                "13": "Perisic I.",
                "14": ""
            },
            "formazione schierata": "√"
        },
        "Pietro": {
            "link": "https://www.fanta.soccer/it/lega/privata/122355/dettaglipartita/18/10535619/",
            "titolari": {
                "1": "Gollini P.",
                "2": "Manolas K.",
                "3": "Godin D.",
                "4": "Ibanez",
                "5": "Bastoni A.",
                "6": "Milinkovic S.",
                "7": "Ramsey A.",
                "8": "Eriksen C.",
                "9": "Simy",
                "10": "Lozano H.",
                "11": "Lukaku R."
            },
            "riserve": {
                "1": "Rossi F.",
                "2": "Sportiello M.",
                "3": "Glik K.",
                "4": "Gabbia M.",
                "5": "Kurtic J.",
                "6": "Sottil R.",
                "7": "Schouten J.",
                "8": "Linetty K.",
                "9": "Correa C.",
                "10": "Iago Falque",
                "11": "",
                "12": "",
                "13": "",
                "14": ""
            },
            "formazione schierata": "√"
        },
        "Gracis": {
            "link": "https://www.fanta.soccer/it/lega/privata/122355/dettaglipartita/18/10535620/",
            "titolari": {
                "1": "Audero E.",
                "2": "Hateboer H.",
                "3": "Romagnoli A.",
                "4": "Lazzari M.",
                "5": "Zappacosta D.",
                "6": "Chiesa F.",
                "7": "Saelemaekers A.",
                "8": "Veretout J.",
                "9": "Ilicic J.",
                "10": "Insigne L.",
                "11": "Leao R."
            },
            "riserve": {
                "1": "Cragno A.",
                "2": "Marusic A.",
                "3": "Palomino J.",
                "4": "Lazovic D.",
                "5": "Miranchuk A.",
                "6": "Maldini D.",
                "7": "Morata A.",
                "8": "Kalulu P.",
                "9": "",
                "10": "",
                "11": "",
                "12": "",
                "13": "",
                "14": ""
            },
            "formazione schierata": "√"
        },
        "Zone": {
            "link": "https://www.fanta.soccer/it/lega/privata/122355/dettaglipartita/18/10535620/",
            "titolari": {
                "1": "Reina P.",
                "2": "Cuadrado J.",
                "3": "Ferrari G.",
                "4": "Spinazzola L.",
                "5": "Milenkovic N.",
                "6": "Castrovilli G.",
                "7": "Badelj M.",
                "8": "Sensi S.",
                "9": "Joao Pedro",
                "10": "Mertens D.",
                "11": "Muriel L."
            },
            "riserve": {
                "1": "Strakosha T.",
                "2": "Mirante A.",
                "3": "Anderson D.",
                "4": "Ruiz F.",
                "5": "Destro M.",
                "6": "De Vrij S.",
                "7": "Peluso F.",
                "8": "Juan Jesus",
                "9": "Alves B.",
                "10": "Zajc M.",
                "11": "Obiang P.",
                "12": "",
                "13": "",
                "14": ""
            },
            "formazione schierata": "√"
        }
    }
}