{
    "Giornata30": {
        "Sangio": {
            "link": "https://www.fanta.soccer/it/lega/privata/119084/dettaglipartita/30/10600916/",
            "titolari": {
                "1": "Silvestri M.",
                "2": "Kumbulla M.",
                "3": "Izzo A.",
                "4": "Kjaer S.",
                "5": "Cuadrado J.",
                "6": "Mkhitaryan H.",
                "7": "Djuricic F.",
                "8": "Ramsey A.",
                "9": "Zapata D.",
                "10": "Politano M.",
                "11": "Lozano H."
            },
            "riserve": {
                "1": "Begovic A.",
                "2": "Donnarumma G.",
                "3": "Faraoni D.",
                "4": "Hysaj E.",
                "5": "Musacchio M.",
                "6": "Pisacane F.",
                "7": "Rossettini L.",
                "8": "Amrabat S.",
                "9": "Perotti D.",
                "10": "Sensi S.",
                "11": "Traore H.",
                "12": "Balotelli M.",
                "13": "Leao R.",
                "14": "Sanabria A."
            },
            "formazione schierata": "X"
        },
        "Milo": {
            "link": "https://www.fanta.soccer/it/lega/privata/119084/dettaglipartita/30/10600916/",
            "titolari": {
                "1": "Szczesny W.",
                "2": "Gosens R.",
                "3": "Lucioni F.",
                "4": "Nuytinck B.",
                "5": "Ansaldi C.",
                "6": "Brozovic M.",
                "7": "Kucka J.",
                "8": "Kurtic J.",
                "9": "Young A.",
                "10": "Ronaldo C.",
                "11": "Barrow M."
            },
            "riserve": {
                "1": "Buffon G.",
                "2": "Pinsoglio C.",
                "3": "Alves B.",
                "4": "Dalbert H.",
                "5": "Castagne T.",
                "6": "Troost-Ekong W.",
                "7": "Zapata C.",
                "8": "Ionita A.",
                "9": "Lobotka S.",
                "10": "Matuidi B.",
                "11": "Higuain G.",
                "12": "Cutrone P.",
                "13": "Paloschi A.",
                "14": "Santander F."
            },
            "formazione schierata": "√"
        },
        "Giulio": {
            "link": "https://www.fanta.soccer/it/lega/privata/119084/dettaglipartita/30/10600917/",
            "titolari": {
                "1": "Musso J.",
                "2": "Hernández T.",
                "3": "Alex Sandro",
                "4": "Rrahmani A.",
                "5": "De Paul R.",
                "6": "Alberto L.",
                "7": "Ribery F.",
                "8": "Schone L.",
                "9": "Insigne L.",
                "10": "Joao Pedro",
                "11": "Okaka S."
            },
            "riserve": {
                "1": "Gollini P.",
                "2": "Sportiello M.",
                "3": "Murru N.",
                "4": "Augello T.",
                "5": "Tripaldelli A.",
                "6": "Berenguer A.",
                "7": "Borini F.",
                "8": "Castro L.",
                "9": "Sema K.",
                "10": "Lapadula G.",
                "11": "Pavoletti L.",
                "12": "Correa C.",
                "13": "Criscito D.",
                "14": "Romagna F."
            },
            "formazione schierata": "√"
        },
        "Melis": {
            "link": "https://www.fanta.soccer/it/lega/privata/119084/dettaglipartita/30/10600917/",
            "titolari": {
                "1": "Strakosha T.",
                "2": "Acerbi F.",
                "3": "Conti A.",
                "4": "Kolarov A.",
                "5": "Palomino J.",
                "6": "Gomez A.",
                "7": "Pulgar E.",
                "8": "Kluivert J.",
                "9": "Belotti A.",
                "10": "Berardi D.",
                "11": "Cornelius A."
            },
            "riserve": {
                "1": "Sansone N.",
                "2": "Palacio R.",
                "3": "Under C.",
                "4": "Missiroli S.",
                "5": "Vieira R.",
                "6": "Benassi M.",
                "7": "Spinazzola L.",
                "8": "Calabria D.",
                "9": "Sabelli S.",
                "10": "Cistana A.",
                "11": "Proto S.",
                "12": "Guerrieri G.",
                "13": "",
                "14": ""
            },
            "formazione schierata": "√"
        },
        "Carlo": {
            "link": "https://www.fanta.soccer/it/lega/privata/119084/dettaglipartita/30/10600918/",
            "titolari": {
                "1": "Perin M.",
                "2": "Larsen J.",
                "3": "Gagliolo R.",
                "4": "Pezzella Ge.",
                "5": "Eriksen C.",
                "6": "Nainggolan R.",
                "7": "Zaniolo N.",
                "8": "Castrovilli G.",
                "9": "Petagna A.",
                "10": "Milik A.",
                "11": "Ilicic J."
            },
            "riserve": {
                "1": "Dragowski B.",
                "2": "Terracciano P.",
                "3": "Caceres M.",
                "4": "Romagnoli A.",
                "5": "Masiello A.",
                "6": "Radu S.",
                "7": "Bani M.",
                "8": "Zielinski P.",
                "9": "Tonali S.",
                "10": "Cassata F.",
                "11": "Zennaro M.",
                "12": "Muriel L.",
                "13": "",
                "14": ""
            },
            "formazione schierata": "√"
        },
        "Bisca": {
            "link": "https://www.fanta.soccer/it/lega/privata/119084/dettaglipartita/30/10600918/",
            "titolari": {
                "1": "Cragno A.",
                "2": "Bastoni A.",
                "3": "Hateboer H.",
                "4": "Manolas K.",
                "5": "Ramirez G.",
                "6": "Veretout J.",
                "7": "Nandez N",
                "8": "Freuler R.",
                "9": "Caicedo F.",
                "10": "Dybala P.",
                "11": "Orsolini R."
            },
            "riserve": {
                "1": "Sirigu S.",
                "2": "Ujkani S.",
                "3": "Skriniar M.",
                "4": "Calderoni M.",
                "5": "Luiz Felipe R.",
                "6": "Pirola L.",
                "7": "Smalling C.",
                "8": "Pjanic M.",
                "9": "Bentancur R.",
                "10": "Pereiro G.",
                "11": "Verdi S.",
                "12": "Quagliarella F.",
                "13": "Esposito S.",
                "14": "Edera S."
            },
            "formazione schierata": "√"
        },
        "Michelone": {
            "link": "https://www.fanta.soccer/it/lega/privata/119084/dettaglipartita/30/10600919/",
            "titolari": {
                "1": "Audero E.",
                "2": "De Vrij S.",
                "3": "Bonucci L.",
                "4": "Dimarco F.",
                "5": "Candreva A.",
                "6": "Douglas Costa",
                "7": "Ruiz F.",
                "8": "Pessina M.",
                "9": "Pinamonti A.",
                "10": "Lukaku R.",
                "11": "Torregrossa E."
            },
            "riserve": {
                "1": "Iago F.",
                "2": "Caputo F.",
                "3": "Caprari G.",
                "4": "Lazovic D.",
                "5": "Barak A.",
                "6": "Lazzari M.",
                "7": "D'Ambrosio D.",
                "8": "Bonifazi K.",
                "9": "Soumaoro A.",
                "10": "Colombi S.",
                "11": "Radu I.",
                "12": "",
                "13": "",
                "14": ""
            },
            "formazione schierata": "√"
        },
        "Zone": {
            "link": "https://www.fanta.soccer/it/lega/privata/119084/dettaglipartita/30/10600919/",
            "titolari": {
                "1": "Handanovic S.",
                "2": "Toloi R.",
                "3": "Darmian M.",
                "4": "De Ligt M.",
                "5": "Calhanoglu H.",
                "6": "Rabiot A.",
                "7": "Pandev G.",
                "8": "Callejon J.",
                "9": "Boga J.",
                "10": "Immobile C.",
                "11": "Sanchez A."
            },
            "riserve": {
                "1": "Padelli D.",
                "2": "Berni T.",
                "3": "Kyriakopoulos G.",
                "4": "Rui M.",
                "5": "Godin D.",
                "6": "Lirola P.",
                "7": "Pasalic M.",
                "8": "Verre V.",
                "9": "Bonaventura G.",
                "10": "Lulic S.",
                "11": "Perez C.",
                "12": "Babacar K.",
                "13": "Defrel G.",
                "14": ""
            },
            "formazione schierata": "√"
        },
        "Zino": {
            "link": "https://www.fanta.soccer/it/lega/privata/119084/dettaglipartita/30/10600920/",
            "titolari": {
                "1": "Lopez P.",
                "2": "Djimsiti B.",
                "3": "Koulibaly K.",
                "4": "Mancini G.",
                "5": "Kulusevski D.",
                "6": "Milinkovic S.",
                "7": "Malinovskyi R.",
                "8": "Pellegrini Lo.",
                "9": "Rebic A.",
                "10": "Martinez L.",
                "11": "Mertens D."
            },
            "riserve": {
                "1": "Mirante A.",
                "2": "Joronen J.",
                "3": "Pellegrini Lu.",
                "4": "Sala J.",
                "5": "Sutalo B.",
                "6": "Nkoulou N.",
                "7": "Lyanco S.",
                "8": "Elmas E.",
                "9": "Locatelli M.",
                "10": "Demme D.",
                "11": "De Roon M.",
                "12": "Lasagna K.",
                "13": "Vlahovic D.",
                "14": "Gabbiadini M."
            },
            "formazione schierata": "√"
        },
        "Pietro": {
            "link": "https://www.fanta.soccer/it/lega/privata/119084/dettaglipartita/30/10600920/",
            "titolari": {
                "1": "Meret A.",
                "2": "Di Lorenzo G.",
                "3": "Caldara M.",
                "4": "Milenkovic N.",
                "5": "Toljan J.",
                "6": "Chiesa F.",
                "7": "Rog M.",
                "8": "Mancosu M.",
                "9": "Simeone G.",
                "10": "Ibrahimovic Z.",
                "11": "Dzeko E."
            },
            "riserve": {
                "1": "Karnezis O.",
                "2": "Ospina D.",
                "3": "Danilo L.",
                "4": "Vicari F.",
                "5": "Iacoponi S.",
                "6": "Donati G.",
                "7": "Linetty K.",
                "8": "Barella N.",
                "9": "Saponara R.",
                "10": "Dabo B.",
                "11": "Soriano R.",
                "12": "Falco F.",
                "13": "Raspadori G.",
                "14": "Millico V."
            },
            "formazione schierata": "X"
        }
    }
}